simplebot_tggroups/__init__.py
simplebot_tggroups/_version.py
simplebot_tggroups/orm.py
simplebot_tggroups/subcommands.py
simplebot_tggroups/util.py
simplebot_tggroups-0.3.0.dist-info/LICENSE
simplebot_tggroups-0.3.0.dist-info/METADATA
simplebot_tggroups-0.3.0.dist-info/WHEEL
simplebot_tggroups-0.3.0.dist-info/entry_points.txt
simplebot_tggroups-0.3.0.dist-info/top_level.txt
simplebot_tggroups-0.3.0.dist-info/RECORD
